py_irt/__init__.py
py_irt/cli.py
py_irt/config.py
py_irt/dataset.py
py_irt/initializers.py
py_irt/io.py
py_irt/models/__init__.py
py_irt/models/abstract_model.py
py_irt/models/amortized_1pl.py
py_irt/models/four_param_logistic.py
py_irt/models/multidim_2pl.py
py_irt/models/one_param_logistic.py
py_irt/models/three_param_logistic.py
py_irt/models/tutorial_model.py
py_irt/models/two_param_logistic.py
py_irt/scoring.py
py_irt/training.py
py_irt-0.6.6.dist-info/LICENSE
py_irt-0.6.6.dist-info/METADATA
py_irt-0.6.6.dist-info/WHEEL
py_irt-0.6.6.dist-info/entry_points.txt
py_irt-0.6.6.dist-info/RECORD
