Metadata-Version: 2.3
Name: py-irt
Version: 0.6.6
Summary: Bayesian IRT models in Python
License: MIT
Author: John P. Lalor
Author-email: john.lalor@nd.edu
Requires-Python: >=3.9,<3.12
Classifier: License :: OSI Approved :: MIT License
Classifier: Programming Language :: Python :: 3
Classifier: Programming Language :: Python :: 3.9
Classifier: Programming Language :: Python :: 3.10
Classifier: Programming Language :: Python :: 3.11
Requires-Dist: numpy (>=1.24.4)
Requires-Dist: ordered-set (>=4.1.0,<5.0.0)
Requires-Dist: pandas (>=2.0.3,<3.0.0)
Requires-Dist: pydantic (>=2.5.3,<3.0.0)
Requires-Dist: pyro-ppl (>=1.8.6,<2.0.0)
Requires-Dist: rich (>=13.7.0,<14.0.0)
Requires-Dist: scikit-learn (>=1.3.2,<2.0.0)
Requires-Dist: scipy (>=1.6.3,<2.0.0)
Requires-Dist: toml (>=0.10.2,<0.11.0)
Requires-Dist: torch (>=2.2.0,<3.0.0)
Requires-Dist: typer (>=0.9.0,<0.15.0)
Project-URL: Homepage, https://github.com/nd-ball/py-irt/
